README.rst
setup.cfg
setup.py
ibsng/__init__.py
ibsng/connection/__init__.py
ibsng/connection/connection.py
ibsng/connection/request.py
ibsng/connection/session.py
ibsng/exception/__init__.py
ibsng/exception/auth.py
ibsng/exception/base.py
ibsng/exception/connection.py
ibsng/exception/general.py
ibsng/exception/handler.py
ibsng/exception/method.py
ibsng/exception/response.py
ibsng/exception/unknown.py
ibsng/handler/__init__.py
ibsng/handler/control.py
ibsng/handler/handler.py
ibsng/handler/initiator.py
ibsng/handler/admin/__init__.py
ibsng/handler/admin/add_new_admin.py
ibsng/handler/admin/change_password.py
ibsng/handler/admin/delete_admin.py
ibsng/handler/admin/expire_all_admin_o_t_ps.py
ibsng/handler/admin/generate_o_t_p.py
ibsng/handler/admin/get_admin_i_s_p_i_d.py
ibsng/handler/admin/get_admin_info.py
ibsng/handler/admin/get_all_admin_infos.py
ibsng/handler/admin/get_all_admin_usernames.py
ibsng/handler/admin/search_o_t_ps.py
ibsng/handler/admin/update_admin_info.py
ibsng/handler/appnama/__init__.py
ibsng/handler/appnama/get_apps_by_charge_id.py
ibsng/handler/appnama/get_associated_apps_to_categories_by_charge_id.py
ibsng/handler/bw/__init__.py
ibsng/handler/bw/add_bw_static_i_p.py
ibsng/handler/bw/add_interface.py
ibsng/handler/bw/add_leaf.py
ibsng/handler/bw/add_leaf_service.py
ibsng/handler/bw/add_node.py
ibsng/handler/bw/del_bw_static_i_p.py
ibsng/handler/bw/del_interface.py
ibsng/handler/bw/del_leaf.py
ibsng/handler/bw/del_leaf_service.py
ibsng/handler/bw/del_node.py
ibsng/handler/bw/get_active_leaves.py
ibsng/handler/bw/get_all_bw_static_i_ps.py
ibsng/handler/bw/get_all_leaf_names.py
ibsng/handler/bw/get_bw_static_i_p_info.py
ibsng/handler/bw/get_interfaces.py
ibsng/handler/bw/get_leaf_charges.py
ibsng/handler/bw/get_leaf_info.py
ibsng/handler/bw/get_node_info.py
ibsng/handler/bw/get_real_host_interfaces.py
ibsng/handler/bw/get_tree.py
ibsng/handler/bw/update_bw_static_i_p.py
ibsng/handler/bw/update_interface.py
ibsng/handler/bw/update_leaf.py
pyibsng.egg-info/PKG-INFO
pyibsng.egg-info/SOURCES.txt
pyibsng.egg-info/dependency_links.txt
pyibsng.egg-info/requires.txt
pyibsng.egg-info/top_level.txt
