Metadata-Version: 1.1
Name: pyibsng
Version: 1.2.6
Summary: IBSng python driver
Home-page: https://github.com/ParspooyeshFanavar/pyibsng
Author: Parspooyesh Fanavar
Author-email: info@parspooyesh.com
License: MIT
Keywords: ibsng,driver,library,json-rpc,rpc
Platform: UNKNOWN
Classifier: Development Status :: 5 - Production/Stable
Classifier: Environment :: Console
Classifier: License :: OSI Approved :: MIT License
Classifier: Operating System :: POSIX
Classifier: Operating System :: POSIX :: Linux
Classifier: Operating System :: MacOS :: MacOS X
Classifier: Operating System :: Microsoft :: Windows
Classifier: Programming Language :: Python :: 2.7
Classifier: Programming Language :: Python :: 3.3
Classifier: Programming Language :: Python :: 3.4
Classifier: Programming Language :: Python :: 3.5
Classifier: Programming Language :: Python :: 3.6
Classifier: Topic :: Terminals
Classifier: Intended Audience :: Developers
